{
  "graphs" : [
    {
      "id" : "urn:clique:62946e9033b5db36555d39538227125fbbed6c910ca07b0cc134e8262f78eb01",
      "nodes" : [
        {
          "id" : "SCTID:40122008",
          "type" : "CLASS"
        },
        {
          "id" : "NCIT:C26861",
          "type" : "CLASS"
        },
        {
          "id" : "MONDO:0015926",
          "type" : "CLASS",
          "lbl" : "pneumoconiosis"
        },
        {
          "id" : "UMLS:C0032273",
          "type" : "CLASS"
        },
        {
          "id" : "MESH:D011009",
          "type" : "CLASS"
        },
        {
          "id" : "Orphanet:182098",
          "type" : "CLASS"
        },
        {
          "id" : "DOID:10316",
          "type" : "CLASS"
        }
      ],
      "edges" : [
        {
          "sub" : "MONDO:0015926",
          "pred" : "owl:equivalentClass",
          "obj" : "Orphanet:182098",
          "meta" : {
            "basicPropertyValues" : [
              {
                "pred" : "https://w3id.org/kgviz/penwidth",
                "val" : 9.9
              }
            ]
          }
        },
        {
          "sub" : "MONDO:0015926",
          "pred" : "owl:equivalentClass",
          "obj" : "NCIT:C26861",
          "meta" : {
            "basicPropertyValues" : [
              {
                "pred" : "https://w3id.org/kgviz/penwidth",
                "val" : 9.9
              }
            ]
          }
        },
        {
          "sub" : "DOID:10316",
          "pred" : "owl:equivalentClass",
          "obj" : "MONDO:0015926",
          "meta" : {
            "basicPropertyValues" : [
              {
                "pred" : "https://w3id.org/kgviz/penwidth",
                "val" : 9.9
              }
            ]
          }
        },
        {
          "sub" : "SCTID:40122008",
          "pred" : "owl:equivalentClass",
          "obj" : "MONDO:0015926",
          "meta" : {
            "basicPropertyValues" : [
              {
                "pred" : "https://w3id.org/kgviz/penwidth",
                "val" : 9.9
              }
            ]
          }
        },
        {
          "sub" : "MESH:D011009",
          "pred" : "owl:equivalentClass",
          "obj" : "MONDO:0015926",
          "meta" : {
            "basicPropertyValues" : [
              {
                "pred" : "https://w3id.org/kgviz/penwidth",
                "val" : 9.9
              }
            ]
          }
        },
        {
          "sub" : "UMLS:C0032273",
          "pred" : "owl:equivalentClass",
          "obj" : "MONDO:0015926",
          "meta" : {
            "basicPropertyValues" : [
              {
                "pred" : "https://w3id.org/kgviz/penwidth",
                "val" : 9.9
              }
            ]
          }
        }
      ],
      "equivalentNodesSets" : [
        {
          "nodeIds" : [
            "MESH:D011009",
            "DOID:10316",
            "MONDO:0015926",
            "UMLS:C0032273",
            "NCIT:C26861",
            "SCTID:40122008",
            "Orphanet:182098"
          ]
        }
      ]
    }
  ]
}