{
  "graphs" : [
    {
      "id" : "urn:clique:923db2a96acfa36db072b4d57345a4bc7e0b4a4aa9723c42a13538c47d9dea1f",
      "nodes" : [
        {
          "id" : "OMIM:614171",
          "type" : "CLASS"
        },
        {
          "id" : "Orphanet:280663",
          "type" : "CLASS"
        },
        {
          "id" : "MONDO:0013606",
          "type" : "CLASS",
          "lbl" : "Hermansky-Pudlak syndrome 9"
        },
        {
          "id" : "UMLS:C3280026",
          "type" : "CLASS"
        },
        {
          "id" : "DOID:0060547",
          "type" : "CLASS"
        }
      ],
      "edges" : [
        {
          "sub" : "UMLS:C3280026",
          "pred" : "owl:equivalentClass",
          "obj" : "MONDO:0013606",
          "meta" : {
            "basicPropertyValues" : [
              {
                "pred" : "https://w3id.org/kgviz/penwidth",
                "val" : 9.9
              }
            ]
          }
        },
        {
          "sub" : "DOID:0060547",
          "pred" : "owl:equivalentClass",
          "obj" : "MONDO:0013606",
          "meta" : {
            "basicPropertyValues" : [
              {
                "pred" : "https://w3id.org/kgviz/penwidth",
                "val" : 9.9
              }
            ]
          }
        },
        {
          "sub" : "MONDO:0013606",
          "pred" : "owl:equivalentClass",
          "obj" : "Orphanet:280663",
          "meta" : {
            "basicPropertyValues" : [
              {
                "pred" : "https://w3id.org/kgviz/penwidth",
                "val" : 9.9
              }
            ]
          }
        },
        {
          "sub" : "MONDO:0013606",
          "pred" : "owl:equivalentClass",
          "obj" : "OMIM:614171",
          "meta" : {
            "basicPropertyValues" : [
              {
                "pred" : "https://w3id.org/kgviz/penwidth",
                "val" : 9.9
              }
            ]
          }
        }
      ],
      "equivalentNodesSets" : [
        {
          "nodeIds" : [
            "Orphanet:280663",
            "MONDO:0013606",
            "OMIM:614171",
            "DOID:0060547",
            "UMLS:C3280026"
          ]
        }
      ]
    }
  ]
}