{
  "graphs" : [
    {
      "id" : "urn:clique:36263763f98e06b42495c32f8461766e59c476e630ae849a456ebdb1731e7d8b",
      "nodes" : [
        {
          "id" : "Orphanet:309854",
          "type" : "CLASS",
          "lbl" : "Cirrhosis-dystonia-polycythemia-hypermanganesemia syndrome"
        },
        {
          "id" : "UMLS:CN035550",
          "type" : "CLASS"
        },
        {
          "id" : "SCTID:702377007",
          "type" : "CLASS"
        },
        {
          "id" : "OMIM:613280",
          "type" : "CLASS"
        },
        {
          "id" : "MONDO:0013208",
          "type" : "CLASS",
          "lbl" : "cirrhosis - dystonia - polycythemia - hypermanganesemia syndrome"
        },
        {
          "id" : "DOID:0080536",
          "type" : "CLASS"
        },
        {
          "id" : "MESH:C548016",
          "type" : "CLASS"
        }
      ],
      "edges" : [
        {
          "sub" : "SCTID:702377007",
          "pred" : "owl:equivalentClass",
          "obj" : "MONDO:0013208",
          "meta" : {
            "basicPropertyValues" : [
              {
                "pred" : "https://w3id.org/kgviz/penwidth",
                "val" : 9.9
              }
            ]
          }
        },
        {
          "sub" : "MONDO:0013208",
          "pred" : "owl:equivalentClass",
          "obj" : "OMIM:613280",
          "meta" : {
            "basicPropertyValues" : [
              {
                "pred" : "https://w3id.org/kgviz/penwidth",
                "val" : 9.9
              }
            ]
          }
        },
        {
          "sub" : "MESH:C548016",
          "pred" : "owl:equivalentClass",
          "obj" : "MONDO:0013208",
          "meta" : {
            "basicPropertyValues" : [
              {
                "pred" : "https://w3id.org/kgviz/penwidth",
                "val" : 9.9
              }
            ]
          }
        },
        {
          "sub" : "MONDO:0013208",
          "pred" : "owl:equivalentClass",
          "obj" : "Orphanet:309854",
          "meta" : {
            "basicPropertyValues" : [
              {
                "pred" : "https://w3id.org/kgviz/penwidth",
                "val" : 9.9
              }
            ]
          }
        },
        {
          "sub" : "DOID:0080536",
          "pred" : "owl:equivalentClass",
          "obj" : "MONDO:0013208",
          "meta" : {
            "basicPropertyValues" : [
              {
                "pred" : "https://w3id.org/kgviz/penwidth",
                "val" : 9.9
              }
            ]
          }
        },
        {
          "sub" : "UMLS:CN035550",
          "pred" : "owl:equivalentClass",
          "obj" : "MONDO:0013208",
          "meta" : {
            "basicPropertyValues" : [
              {
                "pred" : "https://w3id.org/kgviz/penwidth",
                "val" : 9.9
              }
            ]
          }
        }
      ],
      "equivalentNodesSets" : [
        {
          "nodeIds" : [
            "MESH:C548016",
            "UMLS:CN035550",
            "MONDO:0013208",
            "OMIM:613280",
            "Orphanet:309854",
            "SCTID:702377007",
            "DOID:0080536"
          ]
        }
      ]
    }
  ]
}