{
  "graphs" : [
    {
      "id" : "urn:clique:512b683eee7b023e70a16f440ca8c5653887386e8e9443306fcb065f1cb275cd",
      "nodes" : [
        {
          "id" : "SCTID:134031000119108",
          "type" : "CLASS"
        },
        {
          "id" : "MONDO:0006193",
          "type" : "CLASS",
          "lbl" : "endometrial hyperplasia without atypia"
        },
        {
          "id" : "NCIT:C40157",
          "type" : "CLASS",
          "lbl" : "Endometrial Hyperplasia without Atypia"
        }
      ],
      "edges" : [
        {
          "sub" : "MONDO:0006193",
          "pred" : "owl:equivalentClass",
          "obj" : "NCIT:C40157",
          "meta" : {
            "basicPropertyValues" : [
              {
                "pred" : "https://w3id.org/kgviz/penwidth",
                "val" : 9.9
              }
            ]
          }
        },
        {
          "sub" : "SCTID:134031000119108",
          "pred" : "owl:equivalentClass",
          "obj" : "MONDO:0006193",
          "meta" : {
            "basicPropertyValues" : [
              {
                "pred" : "https://w3id.org/kgviz/penwidth",
                "val" : 9.9
              }
            ]
          }
        }
      ],
      "equivalentNodesSets" : [
        {
          "nodeIds" : [
            "MONDO:0006193",
            "NCIT:C40157",
            "SCTID:134031000119108"
          ]
        }
      ]
    }
  ]
}