{
  "graphs" : [
    {
      "id" : "urn:clique:99116ad1576677effad62c20f3d32cb9e46d63da324e4ebb6c71f00e7f183fcd",
      "nodes" : [
        {
          "id" : "MESH:D010003",
          "type" : "CLASS"
        },
        {
          "id" : "SCTID:396275006",
          "type" : "CLASS"
        },
        {
          "id" : "DOID:8398",
          "type" : "CLASS"
        },
        {
          "id" : "ICD10CM:M15-M19",
          "type" : "CLASS"
        },
        {
          "id" : "UMLS:C0029408",
          "type" : "CLASS"
        },
        {
          "id" : "ICD10CM:M19",
          "type" : "CLASS"
        },
        {
          "id" : "MONDO:0005178",
          "type" : "CLASS",
          "lbl" : "osteoarthritis"
        },
        {
          "id" : "NCIT:C3293",
          "type" : "CLASS",
          "lbl" : "Osteoarthritis"
        }
      ],
      "edges" : [
        {
          "sub" : "MESH:D010003",
          "pred" : "owl:equivalentClass",
          "obj" : "MONDO:0005178",
          "meta" : {
            "basicPropertyValues" : [
              {
                "pred" : "https://w3id.org/kgviz/penwidth",
                "val" : 9.9
              }
            ]
          }
        },
        {
          "sub" : "DOID:8398",
          "pred" : "owl:equivalentClass",
          "obj" : "MONDO:0005178",
          "meta" : {
            "basicPropertyValues" : [
              {
                "pred" : "https://w3id.org/kgviz/penwidth",
                "val" : 9.9
              }
            ]
          }
        },
        {
          "sub" : "ICD10CM:M19",
          "pred" : "asserted_is_a",
          "obj" : "ICD10CM:M15-M19",
          "meta" : {
            "basicPropertyValues" : [
            ]
          }
        },
        {
          "sub" : "UMLS:C0029408",
          "pred" : "owl:equivalentClass",
          "obj" : "MONDO:0005178",
          "meta" : {
            "basicPropertyValues" : [
              {
                "pred" : "https://w3id.org/kgviz/penwidth",
                "val" : 9.9
              }
            ]
          }
        },
        {
          "sub" : "ICD10CM:M15-M19",
          "pred" : "owl:equivalentClass",
          "obj" : "MONDO:0005178",
          "meta" : {
            "basicPropertyValues" : [
              {
                "pred" : "https://w3id.org/kgviz/penwidth",
                "val" : 9.9
              }
            ]
          }
        },
        {
          "sub" : "ICD10CM:M19",
          "pred" : "is_a",
          "obj" : "MONDO:0005178",
          "meta" : {
            "basicPropertyValues" : [
              {
                "pred" : "https://w3id.org/kgviz/penwidth",
                "val" : 0.025000000000000022
              }
            ]
          }
        },
        {
          "sub" : "SCTID:396275006",
          "pred" : "owl:equivalentClass",
          "obj" : "MONDO:0005178",
          "meta" : {
            "basicPropertyValues" : [
              {
                "pred" : "https://w3id.org/kgviz/penwidth",
                "val" : 9.9
              }
            ]
          }
        },
        {
          "sub" : "MONDO:0005178",
          "pred" : "owl:equivalentClass",
          "obj" : "NCIT:C3293",
          "meta" : {
            "basicPropertyValues" : [
              {
                "pred" : "https://w3id.org/kgviz/penwidth",
                "val" : 9.9
              }
            ]
          }
        }
      ],
      "equivalentNodesSets" : [
        {
          "nodeIds" : [
            "DOID:8398",
            "MONDO:0005178",
            "ICD10CM:M15-M19",
            "SCTID:396275006",
            "MESH:D010003",
            "NCIT:C3293",
            "UMLS:C0029408"
          ]
        }
      ]
    }
  ]
}