{
  "graphs" : [
    {
      "id" : "urn:clique:b670882133e05b8a6f4d69e61003494d0a4a69e1c2d361393c447a409c39d1ea",
      "nodes" : [
        {
          "id" : "NCIT:C4342",
          "type" : "CLASS",
          "lbl" : "Intravascular Large B-Cell Lymphoma"
        },
        {
          "id" : "UMLS:CN207146",
          "type" : "CLASS"
        },
        {
          "id" : "MONDO:0020324",
          "type" : "CLASS",
          "lbl" : "intravascular large B-cell lymphoma"
        },
        {
          "id" : "Orphanet:98839",
          "type" : "CLASS",
          "lbl" : "Intravascular large B-cell lymphoma"
        },
        {
          "id" : "SCTID:255102004",
          "type" : "CLASS"
        }
      ],
      "edges" : [
        {
          "sub" : "MONDO:0020324",
          "pred" : "owl:equivalentClass",
          "obj" : "Orphanet:98839",
          "meta" : {
            "basicPropertyValues" : [
              {
                "pred" : "https://w3id.org/kgviz/penwidth",
                "val" : 9.9
              }
            ]
          }
        },
        {
          "sub" : "UMLS:CN207146",
          "pred" : "owl:equivalentClass",
          "obj" : "MONDO:0020324",
          "meta" : {
            "basicPropertyValues" : [
              {
                "pred" : "https://w3id.org/kgviz/penwidth",
                "val" : 9.9
              }
            ]
          }
        },
        {
          "sub" : "MONDO:0020324",
          "pred" : "owl:equivalentClass",
          "obj" : "NCIT:C4342",
          "meta" : {
            "basicPropertyValues" : [
              {
                "pred" : "https://w3id.org/kgviz/penwidth",
                "val" : 9.9
              }
            ]
          }
        },
        {
          "sub" : "SCTID:255102004",
          "pred" : "owl:equivalentClass",
          "obj" : "MONDO:0020324",
          "meta" : {
            "basicPropertyValues" : [
              {
                "pred" : "https://w3id.org/kgviz/penwidth",
                "val" : 9.9
              }
            ]
          }
        }
      ],
      "equivalentNodesSets" : [
        {
          "nodeIds" : [
            "Orphanet:98839",
            "SCTID:255102004",
            "UMLS:CN207146",
            "NCIT:C4342",
            "MONDO:0020324"
          ]
        }
      ]
    }
  ]
}