{
  "graphs" : [
    {
      "id" : "urn:clique:cad046e2774fe146cae4738dff7ddefcdc20aaa03384c3a6e69c02634aaacafe",
      "nodes" : [
        {
          "id" : "UMLS:C0221290",
          "type" : "CLASS"
        },
        {
          "id" : "MONDO:0018447",
          "type" : "CLASS",
          "lbl" : "chondromyxoid fibroma"
        },
        {
          "id" : "NCIT:C3830",
          "type" : "CLASS",
          "lbl" : "Chondromyxoid Fibroma"
        },
        {
          "id" : "Orphanet:404507",
          "type" : "CLASS",
          "lbl" : "Chondromyxoid fibroma"
        }
      ],
      "edges" : [
        {
          "sub" : "MONDO:0018447",
          "pred" : "owl:equivalentClass",
          "obj" : "NCIT:C3830",
          "meta" : {
            "basicPropertyValues" : [
              {
                "pred" : "https://w3id.org/kgviz/penwidth",
                "val" : 9.9
              }
            ]
          }
        },
        {
          "sub" : "UMLS:C0221290",
          "pred" : "owl:equivalentClass",
          "obj" : "MONDO:0018447",
          "meta" : {
            "basicPropertyValues" : [
              {
                "pred" : "https://w3id.org/kgviz/penwidth",
                "val" : 9.9
              }
            ]
          }
        },
        {
          "sub" : "MONDO:0018447",
          "pred" : "owl:equivalentClass",
          "obj" : "Orphanet:404507",
          "meta" : {
            "basicPropertyValues" : [
              {
                "pred" : "https://w3id.org/kgviz/penwidth",
                "val" : 9.9
              }
            ]
          }
        }
      ],
      "equivalentNodesSets" : [
        {
          "nodeIds" : [
            "MONDO:0018447",
            "NCIT:C3830",
            "UMLS:C0221290",
            "Orphanet:404507"
          ]
        }
      ]
    }
  ]
}