{
  "graphs" : [
    {
      "id" : "urn:clique:cf36689d4d6401c35a444108bb1eb0fcb6d8f7b885eb800cd63468c312fad4af",
      "nodes" : [
        {
          "id" : "ICD10CM:G37.2",
          "type" : "CLASS"
        },
        {
          "id" : "NCIT:C84623",
          "type" : "CLASS",
          "lbl" : "Central Pontine Myelinolysis"
        },
        {
          "id" : "MESH:D017590",
          "type" : "CLASS"
        },
        {
          "id" : "DOID:636",
          "type" : "CLASS"
        },
        {
          "id" : "MONDO:0006692",
          "type" : "CLASS",
          "lbl" : "central pontine myelinolysis"
        },
        {
          "id" : "SCTID:6807001",
          "type" : "CLASS"
        },
        {
          "id" : "UMLS:C0206083",
          "type" : "CLASS"
        }
      ],
      "edges" : [
        {
          "sub" : "MONDO:0006692",
          "pred" : "owl:equivalentClass",
          "obj" : "NCIT:C84623",
          "meta" : {
            "basicPropertyValues" : [
              {
                "pred" : "https://w3id.org/kgviz/penwidth",
                "val" : 9.9
              }
            ]
          }
        },
        {
          "sub" : "DOID:636",
          "pred" : "owl:equivalentClass",
          "obj" : "MONDO:0006692",
          "meta" : {
            "basicPropertyValues" : [
              {
                "pred" : "https://w3id.org/kgviz/penwidth",
                "val" : 9.9
              }
            ]
          }
        },
        {
          "sub" : "ICD10CM:G37.2",
          "pred" : "owl:equivalentClass",
          "obj" : "MONDO:0006692",
          "meta" : {
            "basicPropertyValues" : [
              {
                "pred" : "https://w3id.org/kgviz/penwidth",
                "val" : 9.9
              }
            ]
          }
        },
        {
          "sub" : "UMLS:C0206083",
          "pred" : "owl:equivalentClass",
          "obj" : "MONDO:0006692",
          "meta" : {
            "basicPropertyValues" : [
              {
                "pred" : "https://w3id.org/kgviz/penwidth",
                "val" : 9.9
              }
            ]
          }
        },
        {
          "sub" : "SCTID:6807001",
          "pred" : "owl:equivalentClass",
          "obj" : "MONDO:0006692",
          "meta" : {
            "basicPropertyValues" : [
              {
                "pred" : "https://w3id.org/kgviz/penwidth",
                "val" : 9.9
              }
            ]
          }
        },
        {
          "sub" : "MESH:D017590",
          "pred" : "owl:equivalentClass",
          "obj" : "MONDO:0006692",
          "meta" : {
            "basicPropertyValues" : [
              {
                "pred" : "https://w3id.org/kgviz/penwidth",
                "val" : 9.9
              }
            ]
          }
        }
      ],
      "equivalentNodesSets" : [
        {
          "nodeIds" : [
            "MONDO:0006692",
            "ICD10CM:G37.2",
            "UMLS:C0206083",
            "SCTID:6807001",
            "NCIT:C84623",
            "MESH:D017590",
            "DOID:636"
          ]
        }
      ]
    }
  ]
}