{
  "graphs" : [
    {
      "id" : "urn:clique:0ffc127fb3144a6778453475527c3c48a3dcfc0e0985c66dbda449b2c7ffeb6c",
      "nodes" : [
        {
          "id" : "MESH:D018126",
          "type" : "CLASS"
        },
        {
          "id" : "SCTID:66063001",
          "type" : "CLASS"
        },
        {
          "id" : "MONDO:0019367",
          "type" : "CLASS",
          "lbl" : "regional odontodysplasia"
        },
        {
          "id" : "Orphanet:83450",
          "type" : "CLASS"
        }
      ],
      "edges" : [
        {
          "sub" : "MESH:D018126",
          "pred" : "owl:equivalentClass",
          "obj" : "MONDO:0019367",
          "meta" : {
            "basicPropertyValues" : [
              {
                "pred" : "https://w3id.org/kgviz/penwidth",
                "val" : 9.9
              }
            ]
          }
        },
        {
          "sub" : "SCTID:66063001",
          "pred" : "owl:equivalentClass",
          "obj" : "MONDO:0019367",
          "meta" : {
            "basicPropertyValues" : [
              {
                "pred" : "https://w3id.org/kgviz/penwidth",
                "val" : 9.9
              }
            ]
          }
        },
        {
          "sub" : "MONDO:0019367",
          "pred" : "owl:equivalentClass",
          "obj" : "Orphanet:83450",
          "meta" : {
            "basicPropertyValues" : [
              {
                "pred" : "https://w3id.org/kgviz/penwidth",
                "val" : 9.9
              }
            ]
          }
        }
      ],
      "equivalentNodesSets" : [
        {
          "nodeIds" : [
            "MESH:D018126",
            "MONDO:0019367",
            "SCTID:66063001",
            "Orphanet:83450"
          ]
        }
      ]
    }
  ]
}