{
  "graphs" : [
    {
      "id" : "urn:clique:2be5b0e3dd3f3804ebf1b8eea879208ef173d1f75ef72bee7129c562303928c0",
      "nodes" : [
        {
          "id" : "MESH:C567819",
          "type" : "CLASS"
        },
        {
          "id" : "UMLS:C2751698",
          "type" : "CLASS"
        },
        {
          "id" : "MONDO:0013077",
          "type" : "CLASS",
          "lbl" : "Santos syndrome"
        },
        {
          "id" : "OMIM:613005",
          "type" : "CLASS"
        }
      ],
      "edges" : [
        {
          "sub" : "MONDO:0013077",
          "pred" : "owl:equivalentClass",
          "obj" : "OMIM:613005",
          "meta" : {
            "basicPropertyValues" : [
              {
                "pred" : "https://w3id.org/kgviz/penwidth",
                "val" : 9.9
              }
            ]
          }
        },
        {
          "sub" : "MESH:C567819",
          "pred" : "owl:equivalentClass",
          "obj" : "MONDO:0013077",
          "meta" : {
            "basicPropertyValues" : [
              {
                "pred" : "https://w3id.org/kgviz/penwidth",
                "val" : 9.9
              }
            ]
          }
        },
        {
          "sub" : "UMLS:C2751698",
          "pred" : "owl:equivalentClass",
          "obj" : "MONDO:0013077",
          "meta" : {
            "basicPropertyValues" : [
              {
                "pred" : "https://w3id.org/kgviz/penwidth",
                "val" : 9.9
              }
            ]
          }
        }
      ],
      "equivalentNodesSets" : [
        {
          "nodeIds" : [
            "OMIM:613005",
            "MONDO:0013077",
            "MESH:C567819",
            "UMLS:C2751698"
          ]
        }
      ]
    }
  ]
}