{
  "graphs" : [
    {
      "id" : "urn:clique:e93b484d4a82f5d6cc4ae29e8a517a56d257abf40b1efae2b78f084c76662eed",
      "nodes" : [
        {
          "id" : "UMLS:CN237509",
          "type" : "CLASS"
        },
        {
          "id" : "Orphanet:423786",
          "type" : "CLASS"
        },
        {
          "id" : "MONDO:0018504",
          "type" : "CLASS",
          "lbl" : "undifferentiated carcinoma of stomach"
        },
        {
          "id" : "UMLS:C1336858",
          "type" : "CLASS"
        },
        {
          "id" : "SCTID:766757006",
          "type" : "CLASS"
        },
        {
          "id" : "NCIT:C5476",
          "type" : "CLASS"
        }
      ],
      "edges" : [
        {
          "sub" : "MONDO:0018504",
          "pred" : "siblingOf",
          "obj" : "UMLS:CN237509",
          "meta" : {
            "basicPropertyValues" : [
              {
                "pred" : "https://w3id.org/kgviz/penwidth",
                "val" : 0.050000000000000044
              }
            ]
          }
        },
        {
          "sub" : "SCTID:766757006",
          "pred" : "owl:equivalentClass",
          "obj" : "MONDO:0018504",
          "meta" : {
            "basicPropertyValues" : [
              {
                "pred" : "https://w3id.org/kgviz/penwidth",
                "val" : 9.9
              }
            ]
          }
        },
        {
          "sub" : "MONDO:0018504",
          "pred" : "owl:equivalentClass",
          "obj" : "Orphanet:423786",
          "meta" : {
            "basicPropertyValues" : [
              {
                "pred" : "https://w3id.org/kgviz/penwidth",
                "val" : 9.9
              }
            ]
          }
        },
        {
          "sub" : "MONDO:0018504",
          "pred" : "owl:equivalentClass",
          "obj" : "NCIT:C5476",
          "meta" : {
            "basicPropertyValues" : [
              {
                "pred" : "https://w3id.org/kgviz/penwidth",
                "val" : 9.9
              }
            ]
          }
        },
        {
          "sub" : "UMLS:C1336858",
          "pred" : "owl:equivalentClass",
          "obj" : "MONDO:0018504",
          "meta" : {
            "basicPropertyValues" : [
              {
                "pred" : "https://w3id.org/kgviz/penwidth",
                "val" : 9.9
              }
            ]
          }
        }
      ],
      "equivalentNodesSets" : [
        {
          "nodeIds" : [
            "SCTID:766757006",
            "MONDO:0018504",
            "Orphanet:423786",
            "UMLS:C1336858",
            "NCIT:C5476"
          ]
        }
      ]
    }
  ]
}