{
  "graphs" : [
    {
      "id" : "urn:clique:ec97993789ab0955d1f9935600b19723fdb5a323be2e185ebcee54787908df43",
      "nodes" : [
        {
          "id" : "MESH:D008172",
          "type" : "CLASS"
        },
        {
          "id" : "UMLS:C0024116",
          "type" : "CLASS"
        },
        {
          "id" : "MONDO:0005766",
          "type" : "CLASS",
          "lbl" : "fungal lung infectious disease"
        }
      ],
      "edges" : [
        {
          "sub" : "MESH:D008172",
          "pred" : "owl:equivalentClass",
          "obj" : "MONDO:0005766",
          "meta" : {
            "basicPropertyValues" : [
              {
                "pred" : "https://w3id.org/kgviz/penwidth",
                "val" : 9.9
              }
            ]
          }
        },
        {
          "sub" : "UMLS:C0024116",
          "pred" : "owl:equivalentClass",
          "obj" : "MONDO:0005766",
          "meta" : {
            "basicPropertyValues" : [
              {
                "pred" : "https://w3id.org/kgviz/penwidth",
                "val" : 9.9
              }
            ]
          }
        }
      ],
      "equivalentNodesSets" : [
        {
          "nodeIds" : [
            "MESH:D008172",
            "MONDO:0005766",
            "UMLS:C0024116"
          ]
        }
      ]
    }
  ]
}