{
  "graphs" : [
    {
      "id" : "urn:clique:eddc6b0cd0ea680811528abca5fbbb258c3a2c6c7febfad4a00334230a07c2a7",
      "nodes" : [
        {
          "id" : "SCTID:764512003",
          "type" : "CLASS"
        },
        {
          "id" : "MONDO:0019889",
          "type" : "CLASS",
          "lbl" : "distal trisomy 22q"
        },
        {
          "id" : "Orphanet:96109",
          "type" : "CLASS"
        }
      ],
      "edges" : [
        {
          "sub" : "SCTID:764512003",
          "pred" : "owl:equivalentClass",
          "obj" : "MONDO:0019889",
          "meta" : {
            "basicPropertyValues" : [
              {
                "pred" : "https://w3id.org/kgviz/penwidth",
                "val" : 9.9
              }
            ]
          }
        },
        {
          "sub" : "MONDO:0019889",
          "pred" : "owl:equivalentClass",
          "obj" : "Orphanet:96109",
          "meta" : {
            "basicPropertyValues" : [
              {
                "pred" : "https://w3id.org/kgviz/penwidth",
                "val" : 9.9
              }
            ]
          }
        }
      ],
      "equivalentNodesSets" : [
        {
          "nodeIds" : [
            "SCTID:764512003",
            "MONDO:0019889",
            "Orphanet:96109"
          ]
        }
      ]
    }
  ]
}