{
  "graphs" : [
    {
      "id" : "urn:clique:f84a3f20958108af8c506dee9119478d4253a1b8720346164a67a844c7f3449f",
      "nodes" : [
        {
          "id" : "MESH:C537548",
          "type" : "CLASS"
        },
        {
          "id" : "OMIMPS:251300",
          "type" : "CLASS"
        },
        {
          "id" : "NCIT:C132195",
          "type" : "CLASS"
        },
        {
          "id" : "UMLS:C0795949",
          "type" : "CLASS"
        },
        {
          "id" : "DOID:0080694",
          "type" : "CLASS"
        },
        {
          "id" : "MONDO:0009627",
          "type" : "CLASS",
          "lbl" : "Galloway-Mowat syndrome"
        },
        {
          "id" : "Orphanet:2065",
          "type" : "CLASS"
        },
        {
          "id" : "SCTID:721297008",
          "type" : "CLASS"
        }
      ],
      "edges" : [
        {
          "sub" : "UMLS:C0795949",
          "pred" : "owl:equivalentClass",
          "obj" : "MONDO:0009627",
          "meta" : {
            "basicPropertyValues" : [
              {
                "pred" : "https://w3id.org/kgviz/penwidth",
                "val" : 9.9
              }
            ]
          }
        },
        {
          "sub" : "MESH:C537548",
          "pred" : "owl:equivalentClass",
          "obj" : "MONDO:0009627",
          "meta" : {
            "basicPropertyValues" : [
              {
                "pred" : "https://w3id.org/kgviz/penwidth",
                "val" : 9.9
              }
            ]
          }
        },
        {
          "sub" : "MONDO:0009627",
          "pred" : "owl:equivalentClass",
          "obj" : "OMIMPS:251300",
          "meta" : {
            "basicPropertyValues" : [
              {
                "pred" : "https://w3id.org/kgviz/penwidth",
                "val" : 9.9
              }
            ]
          }
        },
        {
          "sub" : "MONDO:0009627",
          "pred" : "owl:equivalentClass",
          "obj" : "Orphanet:2065",
          "meta" : {
            "basicPropertyValues" : [
              {
                "pred" : "https://w3id.org/kgviz/penwidth",
                "val" : 9.9
              }
            ]
          }
        },
        {
          "sub" : "MONDO:0009627",
          "pred" : "owl:equivalentClass",
          "obj" : "NCIT:C132195",
          "meta" : {
            "basicPropertyValues" : [
              {
                "pred" : "https://w3id.org/kgviz/penwidth",
                "val" : 9.9
              }
            ]
          }
        },
        {
          "sub" : "DOID:0080694",
          "pred" : "owl:equivalentClass",
          "obj" : "MONDO:0009627",
          "meta" : {
            "basicPropertyValues" : [
              {
                "pred" : "https://w3id.org/kgviz/penwidth",
                "val" : 9.9
              }
            ]
          }
        },
        {
          "sub" : "SCTID:721297008",
          "pred" : "owl:equivalentClass",
          "obj" : "MONDO:0009627",
          "meta" : {
            "basicPropertyValues" : [
              {
                "pred" : "https://w3id.org/kgviz/penwidth",
                "val" : 9.9
              }
            ]
          }
        }
      ],
      "equivalentNodesSets" : [
        {
          "nodeIds" : [
            "MESH:C537548",
            "DOID:0080694",
            "SCTID:721297008",
            "MONDO:0009627",
            "NCIT:C132195",
            "UMLS:C0795949",
            "OMIMPS:251300",
            "Orphanet:2065"
          ]
        }
      ]
    }
  ]
}