{
  "graphs" : [
    {
      "id" : "urn:clique:2e6948e04ccad4341c8865cca8164157ed7751afa9120ba907b96b1ff9702a3b",
      "nodes" : [
        {
          "id" : "SCTID:63450009",
          "type" : "CLASS"
        },
        {
          "id" : "DOID:0070097",
          "type" : "CLASS"
        },
        {
          "id" : "MESH:C537731",
          "type" : "CLASS"
        },
        {
          "id" : "Orphanet:79433",
          "type" : "CLASS",
          "lbl" : "Oculocutaneous albinism type 3"
        },
        {
          "id" : "MONDO:0008747",
          "type" : "CLASS",
          "lbl" : "oculocutaneous albinism type 3"
        },
        {
          "id" : "OMIM:203290",
          "type" : "CLASS"
        }
      ],
      "edges" : [
        {
          "sub" : "MONDO:0008747",
          "pred" : "owl:equivalentClass",
          "obj" : "OMIM:203290",
          "meta" : {
            "basicPropertyValues" : [
              {
                "pred" : "https://w3id.org/kgviz/penwidth",
                "val" : 9.9
              }
            ]
          }
        },
        {
          "sub" : "DOID:0070097",
          "pred" : "owl:equivalentClass",
          "obj" : "MONDO:0008747",
          "meta" : {
            "basicPropertyValues" : [
              {
                "pred" : "https://w3id.org/kgviz/penwidth",
                "val" : 9.9
              }
            ]
          }
        },
        {
          "sub" : "MESH:C537731",
          "pred" : "owl:equivalentClass",
          "obj" : "MONDO:0008747",
          "meta" : {
            "basicPropertyValues" : [
              {
                "pred" : "https://w3id.org/kgviz/penwidth",
                "val" : 9.9
              }
            ]
          }
        },
        {
          "sub" : "SCTID:63450009",
          "pred" : "owl:equivalentClass",
          "obj" : "MONDO:0008747",
          "meta" : {
            "basicPropertyValues" : [
              {
                "pred" : "https://w3id.org/kgviz/penwidth",
                "val" : 9.9
              }
            ]
          }
        },
        {
          "sub" : "MONDO:0008747",
          "pred" : "owl:equivalentClass",
          "obj" : "Orphanet:79433",
          "meta" : {
            "basicPropertyValues" : [
              {
                "pred" : "https://w3id.org/kgviz/penwidth",
                "val" : 9.9
              }
            ]
          }
        }
      ],
      "equivalentNodesSets" : [
        {
          "nodeIds" : [
            "Orphanet:79433",
            "DOID:0070097",
            "OMIM:203290",
            "MONDO:0008747",
            "SCTID:63450009",
            "MESH:C537731"
          ]
        }
      ]
    }
  ]
}