{
  "graphs" : [
    {
      "id" : "urn:clique:632f28fc3acf05ad9e843011d1eed8d3f84bd47dc4ef0a1a0239085d1a2573c1",
      "nodes" : [
        {
          "id" : "OMIM:311450",
          "type" : "CLASS"
        },
        {
          "id" : "MESH:C538106",
          "type" : "CLASS"
        },
        {
          "id" : "SCTID:719020006",
          "type" : "CLASS"
        },
        {
          "id" : "UMLS:C0796110",
          "type" : "CLASS"
        },
        {
          "id" : "MONDO:0010708",
          "type" : "CLASS",
          "lbl" : "Pallister-W syndrome"
        },
        {
          "id" : "Orphanet:2804",
          "type" : "CLASS"
        }
      ],
      "edges" : [
        {
          "sub" : "UMLS:C0796110",
          "pred" : "owl:equivalentClass",
          "obj" : "MONDO:0010708",
          "meta" : {
            "basicPropertyValues" : [
              {
                "pred" : "https://w3id.org/kgviz/penwidth",
                "val" : 9.9
              }
            ]
          }
        },
        {
          "sub" : "SCTID:719020006",
          "pred" : "owl:equivalentClass",
          "obj" : "MONDO:0010708",
          "meta" : {
            "basicPropertyValues" : [
              {
                "pred" : "https://w3id.org/kgviz/penwidth",
                "val" : 9.9
              }
            ]
          }
        },
        {
          "sub" : "MESH:C538106",
          "pred" : "owl:equivalentClass",
          "obj" : "MONDO:0010708",
          "meta" : {
            "basicPropertyValues" : [
              {
                "pred" : "https://w3id.org/kgviz/penwidth",
                "val" : 9.9
              }
            ]
          }
        },
        {
          "sub" : "MONDO:0010708",
          "pred" : "owl:equivalentClass",
          "obj" : "Orphanet:2804",
          "meta" : {
            "basicPropertyValues" : [
              {
                "pred" : "https://w3id.org/kgviz/penwidth",
                "val" : 9.9
              }
            ]
          }
        },
        {
          "sub" : "MONDO:0010708",
          "pred" : "owl:equivalentClass",
          "obj" : "OMIM:311450",
          "meta" : {
            "basicPropertyValues" : [
              {
                "pred" : "https://w3id.org/kgviz/penwidth",
                "val" : 9.9
              }
            ]
          }
        }
      ],
      "equivalentNodesSets" : [
        {
          "nodeIds" : [
            "Orphanet:2804",
            "UMLS:C0796110",
            "MONDO:0010708",
            "SCTID:719020006",
            "MESH:C538106",
            "OMIM:311450"
          ]
        }
      ]
    }
  ]
}