{
  "graphs" : [
    {
      "id" : "urn:clique:75930cb20bf2b6e657a140a0464ba776e24c802207ff47a7d147467e7b658e8e",
      "nodes" : [
        {
          "id" : "SCTID:89182000",
          "type" : "CLASS"
        },
        {
          "id" : "UMLS:C0155123",
          "type" : "CLASS"
        },
        {
          "id" : "DOID:14507",
          "type" : "CLASS"
        },
        {
          "id" : "MONDO:0001983",
          "type" : "CLASS",
          "lbl" : "peripheral degeneration of cornea"
        }
      ],
      "edges" : [
        {
          "sub" : "DOID:14507",
          "pred" : "owl:equivalentClass",
          "obj" : "MONDO:0001983",
          "meta" : {
            "basicPropertyValues" : [
              {
                "pred" : "https://w3id.org/kgviz/penwidth",
                "val" : 9.9
              }
            ]
          }
        },
        {
          "sub" : "UMLS:C0155123",
          "pred" : "owl:equivalentClass",
          "obj" : "MONDO:0001983",
          "meta" : {
            "basicPropertyValues" : [
              {
                "pred" : "https://w3id.org/kgviz/penwidth",
                "val" : 9.9
              }
            ]
          }
        },
        {
          "sub" : "SCTID:89182000",
          "pred" : "owl:equivalentClass",
          "obj" : "MONDO:0001983",
          "meta" : {
            "basicPropertyValues" : [
              {
                "pred" : "https://w3id.org/kgviz/penwidth",
                "val" : 9.9
              }
            ]
          }
        }
      ],
      "equivalentNodesSets" : [
        {
          "nodeIds" : [
            "DOID:14507",
            "MONDO:0001983",
            "UMLS:C0155123",
            "SCTID:89182000"
          ]
        }
      ]
    }
  ]
}