{
  "graphs" : [
    {
      "id" : "urn:clique:b3b03b183c3924381108796dca1b79576fb64613893a1de823916df7b3abfbed",
      "nodes" : [
        {
          "id" : "MESH:D004767",
          "type" : "CLASS"
        },
        {
          "id" : "SCTID:370514003",
          "type" : "CLASS"
        },
        {
          "id" : "UMLS:C0014371",
          "type" : "CLASS"
        },
        {
          "id" : "MONDO:0006747",
          "type" : "CLASS",
          "lbl" : "enterotoxemia"
        }
      ],
      "edges" : [
        {
          "sub" : "MESH:D004767",
          "pred" : "owl:equivalentClass",
          "obj" : "MONDO:0006747",
          "meta" : {
            "basicPropertyValues" : [
              {
                "pred" : "https://w3id.org/kgviz/penwidth",
                "val" : 9.9
              }
            ]
          }
        },
        {
          "sub" : "SCTID:370514003",
          "pred" : "owl:equivalentClass",
          "obj" : "MONDO:0006747",
          "meta" : {
            "basicPropertyValues" : [
              {
                "pred" : "https://w3id.org/kgviz/penwidth",
                "val" : 9.9
              }
            ]
          }
        },
        {
          "sub" : "UMLS:C0014371",
          "pred" : "owl:equivalentClass",
          "obj" : "MONDO:0006747",
          "meta" : {
            "basicPropertyValues" : [
              {
                "pred" : "https://w3id.org/kgviz/penwidth",
                "val" : 9.9
              }
            ]
          }
        }
      ],
      "equivalentNodesSets" : [
        {
          "nodeIds" : [
            "MONDO:0006747",
            "MESH:D004767",
            "SCTID:370514003",
            "UMLS:C0014371"
          ]
        }
      ]
    }
  ]
}