{
  "graphs" : [
    {
      "id" : "urn:clique:d224eb7d1a59589710960ac4a8d0a5abd28062145724fbb364a23ec85311dc34",
      "nodes" : [
        {
          "id" : "DOID:0110831",
          "type" : "CLASS"
        },
        {
          "id" : "MONDO:0010984",
          "type" : "CLASS",
          "lbl" : "Usher syndrome type 1D"
        },
        {
          "id" : "OMIM:601067",
          "type" : "CLASS"
        }
      ],
      "edges" : [
        {
          "sub" : "DOID:0110831",
          "pred" : "owl:equivalentClass",
          "obj" : "MONDO:0010984",
          "meta" : {
            "basicPropertyValues" : [
              {
                "pred" : "https://w3id.org/kgviz/penwidth",
                "val" : 9.9
              }
            ]
          }
        },
        {
          "sub" : "MONDO:0010984",
          "pred" : "owl:equivalentClass",
          "obj" : "OMIM:601067",
          "meta" : {
            "basicPropertyValues" : [
              {
                "pred" : "https://w3id.org/kgviz/penwidth",
                "val" : 9.9
              }
            ]
          }
        }
      ],
      "equivalentNodesSets" : [
        {
          "nodeIds" : [
            "DOID:0110831",
            "MONDO:0010984",
            "OMIM:601067"
          ]
        }
      ]
    }
  ]
}