{
  "graphs" : [
    {
      "id" : "urn:clique:d4e3e233f2d4da6bc85315ae93a08a7cf8539e4d4f59af551167fa59feba9e24",
      "nodes" : [
        {
          "id" : "MESH:D014786",
          "type" : "CLASS"
        },
        {
          "id" : "NCIT:C35126",
          "type" : "CLASS",
          "lbl" : "Vision Disorder"
        },
        {
          "id" : "MONDO:0021084",
          "type" : "CLASS",
          "lbl" : "vision disorder"
        },
        {
          "id" : "UMLS:C0042790",
          "type" : "CLASS"
        },
        {
          "id" : "SCTID:95677002",
          "type" : "CLASS"
        }
      ],
      "edges" : [
        {
          "sub" : "MESH:D014786",
          "pred" : "owl:equivalentClass",
          "obj" : "MONDO:0021084",
          "meta" : {
            "basicPropertyValues" : [
              {
                "pred" : "https://w3id.org/kgviz/penwidth",
                "val" : 9.9
              }
            ]
          }
        },
        {
          "sub" : "MONDO:0021084",
          "pred" : "owl:equivalentClass",
          "obj" : "NCIT:C35126",
          "meta" : {
            "basicPropertyValues" : [
              {
                "pred" : "https://w3id.org/kgviz/penwidth",
                "val" : 9.9
              }
            ]
          }
        },
        {
          "sub" : "UMLS:C0042790",
          "pred" : "owl:equivalentClass",
          "obj" : "MONDO:0021084",
          "meta" : {
            "basicPropertyValues" : [
              {
                "pred" : "https://w3id.org/kgviz/penwidth",
                "val" : 9.9
              }
            ]
          }
        },
        {
          "sub" : "SCTID:95677002",
          "pred" : "owl:equivalentClass",
          "obj" : "MONDO:0021084",
          "meta" : {
            "basicPropertyValues" : [
              {
                "pred" : "https://w3id.org/kgviz/penwidth",
                "val" : 9.9
              }
            ]
          }
        }
      ],
      "equivalentNodesSets" : [
        {
          "nodeIds" : [
            "MESH:D014786",
            "MONDO:0021084",
            "NCIT:C35126",
            "UMLS:C0042790",
            "SCTID:95677002"
          ]
        }
      ]
    }
  ]
}